MR_Package/__init__.py
MR_Package/file_io.py
MR_Package/logger.py
MR_Package/mail_log.py
MR_Package/math.py
MR_Sidepackage/__init__.py
SimpleMySQL/__init__.py
SimpleMySQL/connect.py
MR_Package-1.1.7.dist-info/LICENSE
MR_Package-1.1.7.dist-info/METADATA
MR_Package-1.1.7.dist-info/WHEEL
MR_Package-1.1.7.dist-info/top_level.txt
MR_Package-1.1.7.dist-info/RECORD
