Metadata-Version: 2.1
Name: MR-Package
Version: 1.1.7
Summary: A small package for easy file IO and maths
Home-page: https://github.com/manuraffl30/MR_Package
Author: Manuel Alexander Christoph Raffl
Author-email: manuraffl003@gmail.com
License: UNKNOWN
Project-URL: Bug Tracker, https://github.com/manuraffl30/MR_Package/issues
Platform: UNKNOWN
Classifier: Programming Language :: Python :: 3
Classifier: License :: OSI Approved :: MIT License
Classifier: Operating System :: OS Independent
Requires-Python: >=3.6
License-File: LICENSE
